{
    "name": "Python Google Cloud Functions Development",
    "build": {
        "dockerfile": "Dockerfile"
    },
    "forwardPorts": [8080],
    "customizations": {
        "vscode": {
            "extensions": [
                "ms-python.python",
                "ms-azuretools.vscode-docker",
                "eamodio.gitlens",
                "mhutchie.git-graph",
                "ms-python.vscode-pylance"
            ],
            "settings": {
                "python.defaultInterpreterPath": "/usr/local/bin/python",
                "python.testing.pytestArgs": [
                    "tests"
                ],
                "python.testing.unittestEnabled": false,
                "python.testing.pytestEnabled": true,
                "python.testing.nosetestsEnabled": false
            }
        }
    },
    "features": {
        "ghcr.io/devcontainers/features/common-utils:2": {
            "installZsh": "true",
            "username": "vscode",
            "upgradePackages": "true",
            "nonFreePackages": "true"
        },
        "ghcr.io/devcontainers/features/git:1": {
            "ppa": true,
            "version": "latest"
        }
    },
    "remoteUser": "vscode",
    "postCreateCommand": "pip install --upgrade pip && pip install -r requirements.txt",
    "runArgs": [
        "--userns=keep-id",
        "--security-opt=label=disable"
    ],
    "workspaceMount": "source=${localWorkspaceFolder},target=/workspace,type=bind,consistency=cached",
    "workspaceFolder": "/workspace",
    "containerEnv": {
        "HOME": "/home/vscode"
    },
    "containerUser": "vscode"
}